[{"id":4,"category":"Bike","subCategory":"Racer","type":"square","wallpaperTitle":"Bike","img":"http://res.cloudinary.com/dwwf3vdpl/image/upload/v1690371113/ort7acwutsriihnlewoz.jpg","wallpaperTags":"Valentine","wallpaperColor":"Red","status":"active"},{"id":5,"category":"Bike","subCategory":"Racer","type":"landscape","wallpaperTitle":"Bike","img":"http://res.cloudinary.com/dwwf3vdpl/image/upload/v1690371424/h9c8fbtowmnu1hojvini.jpg","wallpaperTags":"Racer","wallpaperColor":"Red","status":"inactive"},{"id":6,"category":"Animals","subCategory":"Lion","type":"portrait","wallpaperTitle":"Animals","img":"http://res.cloudinary.com/dwwf3vdpl/image/upload/v1690373096/ubpex5kzsbfwp0okcxpp.jpg","wallpaperTags":"Lion A King","wallpaperColor":"Yellow","status":"active"},{"id":7,"category":"Bike","subCategory":"Racer","type":"portrait","wallpaperTitle":"Bike-Racer","img":"http://res.cloudinary.com/dwwf3vdpl/image/upload/v1690536651/hjothtzuin4mjes2pvma.jpg","wallpaperTags":"racer","wallpaperColor":"Yellow","status":"active"}]